luwi_gym_foo/__init__.py
luwi_gym_foo/envs/__init__.py
luwi_gym_foo/envs/foo_env.py
luwi_gym_foo-0.1.0.dist-info/METADATA
luwi_gym_foo-0.1.0.dist-info/WHEEL
luwi_gym_foo-0.1.0.dist-info/top_level.txt
luwi_gym_foo-0.1.0.dist-info/RECORD
