Metadata-Version: 2.1
Name: luwi-gym-foo
Version: 0.1.0
Summary: A OpenAI Gym Env for foo
Home-page: UNKNOWN
License: UNKNOWN
Platform: UNKNOWN
Requires-Dist: gym
